[
    {
        "title": "The Hard Thing About Things",
        "author": "Ben Horowitz",
        "description": "",
    },
    {
        "title": "The Art of Learning",
        "author": "Josh Waitzkin",
        "description": "",
    },
    {
        "title": "How to Think Like Leonardo da Vinci",
        "author": "Michael J. Gelb",
        "description": "",
    },
    {
        "title": "The Sun Also Rises",
        "author": "Hemingway",
        "description": "",
    },
    {
        "title": "Quantum Electrodynamics",
        "author": "Feyman",
        "description": "",
    },
    {
        "title": "Poker Without Cards",
        "author": "Ben Mack",
        "description": "",
    },
    {
        "title": "The Stranger",
        "author": "Albert Camus",
        "description": "",
    },
    {
        "title": "Cat's Cradle",
        "author": "Kurt Vonnegut",
        "description": "",
    },
    {
        "title": "Taipan",
        "author": "James Clavell",
        "description": "",
    },
    {
        "title": "The Idiot",
        "author": "Dostoyevsky",
        "description": "",
    }
]
